envswitcher.py
envswitcher-0.1.0.dist-info/entry_points.txt
envswitcher-0.1.0.dist-info/WHEEL
envswitcher-0.1.0.dist-info/METADATA
envswitcher-0.1.0.dist-info/RECORD
